colorblender.py
colorblender-0.0.1.dist-info/METADATA
colorblender-0.0.1.dist-info/WHEEL
colorblender-0.0.1.dist-info/licenses/LICENSE
colorblender-0.0.1.dist-info/RECORD
