Metadata-Version: 2.1
Name: colorblender
Version: 0.0.1
Summary: A tool for blending hex colors
Project-URL: Homepage, https://github.com/ChristianChiarulli/colorblender
Project-URL: Bug Tracker, https://github.com/ChristianChiarulli/colorblender/issues
Author-email: Christian Chiarulli <chris.machine@pm.me>
License:                     GNU GENERAL PUBLIC LICENSE
Classifier: Operating System :: OS Independent
Classifier: Programming Language :: Python :: 3
Requires-Python: >=3.7
